README.rst
setup.py
Flask_OpenERP.egg-info/PKG-INFO
Flask_OpenERP.egg-info/SOURCES.txt
Flask_OpenERP.egg-info/dependency_links.txt
Flask_OpenERP.egg-info/namespace_packages.txt
Flask_OpenERP.egg-info/not-zip-safe
Flask_OpenERP.egg-info/requires.txt
Flask_OpenERP.egg-info/top_level.txt
flaskext/__init__.py
flaskext/openerp.py
flaskext/rpc.py