Metadata-Version: 1.1
Name: Flask-OpenERP
Version: 0.3.1
Summary: OpenERP Connector for Flask
Home-page: https://github.com/matrixise/flask-openerp/
Author: Stephane Wirtel
Author-email: stephane@wirtel.be
License: BSD
Platform: any
Classifier: Environment :: Web Environment
Classifier: Intended Audience :: Developers
Classifier: License :: OSI Approved :: BSD License
Classifier: Operating System :: OS Independent
Classifier: Programming Language :: Python
Classifier: Topic :: Internet :: WWW/HTTP :: Dynamic Content
Classifier: Topic :: Software Development :: Libraries :: Python Modules
